{
  "articles": [
    {
      "id": "a-menininha-que-nos-leva-para-casa",
      "title": "A menininha que nos leva para casa",
      "author": "Vladimir Dietrich",
      "date": "2024-04-22",
      "readingTime": 5,
      "heroImage": {
        "fileName": "a-menininha-que-nos-leva-para-casa-image-0.jpg",
        "githubPath": "images/a-menininha-que-nos-leva-para-casa-image-0.jpg",
        "githubUrl": "https://raw.githubusercontent.com/vladimirbrasil/vladidevblog/main/images/a-menininha-que-nos-leva-para-casa-image-0.jpg",
        "altText": "jargões",
        "caption": "jargões"
      },
      "lastUpdated": "2025-06-27T14:10:01.432Z"
    },
    {
      "id": "onde-estamos",
      "title": "Onde estamos?",
      "author": "Vladimir Dietrich",
      "date": "2023-09-19",
      "readingTime": 3,
      "heroImage": {
        "fileName": "onde-estamos-image-0.jpg",
        "githubPath": "images/onde-estamos-image-0.jpg",
        "githubUrl": "https://raw.githubusercontent.com/vladimirbrasil/vladidevblog/main/images/onde-estamos-image-0.jpg",
        "altText": "emptiness.",
        "caption": "emptiness."
      },
      "lastUpdated": "2025-06-27T14:09:13.683Z"
    },
    {
      "id": "auto-traicao",
      "title": "Auto traição?",
      "author": "Vladimir Dietrich",
      "date": "2023-07-15",
      "readingTime": 4,
      "heroImage": {
        "fileName": "auto-traicao-image-0.jpg",
        "githubPath": "images/auto-traicao-image-0.jpg",
        "githubUrl": "https://raw.githubusercontent.com/vladimirbrasil/vladidevblog/main/images/auto-traicao-image-0.jpg",
        "altText": "a terrifying skull transforming into a beautiful heart.",
        "caption": "a terrifying skull transforming into a beautiful heart."
      },
      "lastUpdated": "2025-06-27T14:11:52.279Z"
    },
    {
      "id": "consciencia-entre-as-pernas",
      "title": "Consciência entre as pernas",
      "author": "Vladimir Dietrich",
      "date": "2023-06-08",
      "readingTime": 2,
      "heroImage": {
        "fileName": "consciencia-entre-as-pernas-image-0.jpg",
        "githubPath": "images/consciencia-entre-as-pernas-image-0.jpg",
        "githubUrl": "https://raw.githubusercontent.com/vladimirbrasil/vladidevblog/main/images/consciencia-entre-as-pernas-image-0.jpg",
        "altText": "an humanoid robot barefoot inside a jungle",
        "caption": "an humanoid robot barefoot inside a jungle"
      },
      "lastUpdated": "2025-06-27T14:10:50.438Z"
    },
    {
      "id": "ocio-a-esquerda",
      "title": "Ócio à esquerda",
      "author": "Vladimir Dietrich",
      "date": "2023-05-29",
      "readingTime": 2,
      "heroImage": {
        "fileName": "ocio-a-esquerda-image-0.jpg",
        "githubPath": "images/ocio-a-esquerda-image-0.jpg",
        "githubUrl": "https://raw.githubusercontent.com/vladimirbrasil/vladidevblog/main/images/ocio-a-esquerda-image-0.jpg",
        "altText": "an humanoid robot barefoot inside a jungle",
        "caption": "an humanoid robot barefoot inside a jungle"
      },
      "lastUpdated": "2025-06-27T14:11:35.888Z"
    },
    {
      "id": "caixao-nao-tem-gavetas",
      "title": "Caixão não tem gavetas",
      "author": "Vladimir Dietrich",
      "date": "2023-04-14",
      "readingTime": 4,
      "heroImage": null,
      "lastUpdated": "2025-06-27T14:11:27.158Z"
    },
    {
      "id": "troncos-no-universo",
      "title": "Troncos no universo?",
      "author": "Vladimir Dietrich",
      "date": "2023-04-11",
      "readingTime": 4,
      "heroImage": {
        "fileName": "troncos-no-universo-image-0.png",
        "githubPath": "images/troncos-no-universo-image-0.png",
        "githubUrl": "https://raw.githubusercontent.com/vladimirbrasil/vladidevblog/main/images/troncos-no-universo-image-0.png",
        "altText": "",
        "caption": ""
      },
      "lastUpdated": "2025-06-27T14:08:33.957Z"
    },
    {
      "id": "podemos-ser-traidos-pelo-nosso-dinheiro",
      "title": "Podemos ser traídos pelo nosso dinheiro?",
      "author": "Vladimir Dietrich",
      "date": "2023-03-11",
      "readingTime": 5,
      "heroImage": null,
      "lastUpdated": "2025-06-27T14:11:19.976Z"
    },
    {
      "id": "esquerda-direita-papais-nenens",
      "title": "Esquerda, Direita, Papais, Nenéns",
      "author": "Vladimir Dietrich",
      "date": "2023-03-07",
      "readingTime": 3,
      "heroImage": {
        "fileName": "esquerda-direita-papais-nenens-image-hero.png",
        "githubPath": "images/esquerda-direita-papais-nenens-image-hero.png",
        "githubUrl": "https://raw.githubusercontent.com/vladimirbrasil/vladidevblog/main/images/esquerda-direita-papais-nenens-image-hero.png",
        "altText": "",
        "caption": ""
      },
      "lastUpdated": "2025-06-27T14:11:10.410Z"
    },
    {
      "id": "global-and-focused-social-medias",
      "title": "Global and Focused Social Medias ❤️",
      "author": "Vladimir Dietrich",
      "date": "2022-04-02",
      "readingTime": 1,
      "heroImage": {
        "fileName": "global-and-focused-social-medias-image-0.jpg",
        "githubPath": "images/global-and-focused-social-medias-image-0.jpg",
        "githubUrl": "https://raw.githubusercontent.com/vladimirbrasil/vladidevblog/main/images/global-and-focused-social-medias-image-0.jpg",
        "altText": "",
        "caption": ""
      },
      "lastUpdated": "2025-06-27T14:17:42.030Z"
    },
    {
      "id": "arranha-vaidades",
      "title": "Arranha-[vaidades]",
      "author": "Vladimir Dietrich",
      "date": "2022-03-08",
      "readingTime": 3,
      "heroImage": {
        "fileName": "arranha-vaidades-image-0.jpg",
        "githubPath": "images/arranha-vaidades-image-0.jpg",
        "githubUrl": "https://raw.githubusercontent.com/vladimirbrasil/vladidevblog/main/images/arranha-vaidades-image-0.jpg",
        "altText": "",
        "caption": ""
      },
      "lastUpdated": "2025-06-27T14:18:05.674Z"
    },
    {
      "id": "eugenia-na-comunicacao",
      "title": "🍎 Eugenia na comunicação?",
      "author": "Vladimir Dietrich",
      "date": "2022-02-11",
      "readingTime": 12,
      "heroImage": {
        "fileName": "eugenia-na-comunicacao-image-0.jpg",
        "githubPath": "images/eugenia-na-comunicacao-image-0.jpg",
        "githubUrl": "https://raw.githubusercontent.com/vladimirbrasil/vladidevblog/main/images/eugenia-na-comunicacao-image-0.jpg",
        "altText": "",
        "caption": ""
      },
      "lastUpdated": "2025-06-27T14:35:28.969Z"
    },
    {
      "id": "por-que-cuspir-a-consciencia",
      "title": "Por que cuspir a consciência?",
      "author": "Vladimir Dietrich",
      "date": "2021-11-30",
      "readingTime": 4,
      "heroImage": {
        "fileName": "por-que-cuspir-a-consciencia-image-0.jpg",
        "githubPath": "images/por-que-cuspir-a-consciencia-image-0.jpg",
        "githubUrl": "https://raw.githubusercontent.com/vladimirbrasil/vladidevblog/main/images/por-que-cuspir-a-consciencia-image-0.jpg",
        "altText": "",
        "caption": ""
      },
      "lastUpdated": "2025-06-27T14:20:10.015Z"
    },
    {
      "id": "neuragame",
      "title": "Neuragame",
      "author": "Vladimir Dietrich",
      "date": "2021-11-16",
      "readingTime": 5,
      "heroImage": {
        "fileName": "neuragame-image-0.jpg",
        "githubPath": "images/neuragame-image-0.jpg",
        "githubUrl": "https://raw.githubusercontent.com/vladimirbrasil/vladidevblog/main/images/neuragame-image-0.jpg",
        "altText": "",
        "caption": ""
      },
      "lastUpdated": "2025-06-27T14:35:52.012Z"
    },
    {
      "id": "previsivel",
      "title": "Previsível?",
      "author": "Vladimir Dietrich",
      "date": "2021-11-05",
      "readingTime": 2,
      "heroImage": {
        "fileName": "previsivel-image-0.jpg",
        "githubPath": "images/previsivel-image-0.jpg",
        "githubUrl": "https://raw.githubusercontent.com/vladimirbrasil/vladidevblog/main/images/previsivel-image-0.jpg",
        "altText": "",
        "caption": ""
      },
      "lastUpdated": "2025-06-27T14:36:49.950Z"
    },
    {
      "id": "vanilla-skyourself",
      "title": "Vanilla Skyourself",
      "author": "Vladimir Dietrich",
      "date": "2021-11-04",
      "readingTime": 2,
      "heroImage": {
        "fileName": "vanilla-skyourself-image-0.jpg",
        "githubPath": "images/vanilla-skyourself-image-0.jpg",
        "githubUrl": "https://raw.githubusercontent.com/vladimirbrasil/vladidevblog/main/images/vanilla-skyourself-image-0.jpg",
        "altText": "",
        "caption": ""
      },
      "lastUpdated": "2025-06-27T14:37:08.752Z"
    },
    {
      "id": "sentimento-digital",
      "title": "Sentimento Digital",
      "author": "Vladimir Dietrich",
      "date": "2021-10-23",
      "readingTime": 4,
      "heroImage": {
        "fileName": "sentimento-digital-image-0.jpg",
        "githubPath": "images/sentimento-digital-image-0.jpg",
        "githubUrl": "https://raw.githubusercontent.com/vladimirbrasil/vladidevblog/main/images/sentimento-digital-image-0.jpg",
        "altText": "",
        "caption": ""
      },
      "lastUpdated": "2025-06-27T14:37:30.853Z"
    },
    {
      "id": "aspirar-o-proprio-rabo",
      "title": "Aspirar o próprio rabo?",
      "author": "Vladimir Dietrich",
      "date": "2021-09-25",
      "readingTime": 2,
      "heroImage": {
        "fileName": "aspirar-o-proprio-rabo-image-0.jpg",
        "githubPath": "images/aspirar-o-proprio-rabo-image-0.jpg",
        "githubUrl": "https://raw.githubusercontent.com/vladimirbrasil/vladidevblog/main/images/aspirar-o-proprio-rabo-image-0.jpg",
        "altText": "",
        "caption": ""
      },
      "lastUpdated": "2025-06-27T14:37:39.934Z"
    },
    {
      "id": "esquerda-vs-direita-ou-emocao-vs-razao",
      "title": "Esquerda vs Direita ou Emoção vs Razão?",
      "author": "Vladimir Dietrich",
      "date": "2021-09-10",
      "readingTime": 2,
      "heroImage": {
        "fileName": "esquerda-vs-direita-ou-emocao-vs-razao-image-0.jpg",
        "githubPath": "images/esquerda-vs-direita-ou-emocao-vs-razao-image-0.jpg",
        "githubUrl": "https://raw.githubusercontent.com/vladimirbrasil/vladidevblog/main/images/esquerda-vs-direita-ou-emocao-vs-razao-image-0.jpg",
        "altText": "",
        "caption": ""
      },
      "lastUpdated": "2025-06-27T14:37:45.542Z"
    },
    {
      "id": "qual-e-o-esporte-mais-dificil-do-mundo",
      "title": "Qual é o esporte mais difícil do mundo?",
      "author": "Vladimir Dietrich",
      "date": "2021-05-17",
      "readingTime": 13,
      "heroImage": {
        "fileName": "qual-e-o-esporte-mais-dificil-do-mundo-image-hero.png",
        "githubPath": "images/qual-e-o-esporte-mais-dificil-do-mundo-image-hero.png",
        "githubUrl": "https://raw.githubusercontent.com/vladimirbrasil/vladidevblog/main/images/qual-e-o-esporte-mais-dificil-do-mundo-image-hero.png",
        "altText": "",
        "caption": ""
      },
      "lastUpdated": "2025-06-27T14:38:41.053Z"
    }
  ],
  "lastUpdated": "2025-06-27T14:38:41.064Z"
}